{
  "$schema": "https://turborepo.dev/schema.v2.json",
  "tasks": {
    "build": {
      "dependsOn": ["^build"],
      "outputs": [".next/**", "!.next/cache/**", "dist/**"]
    },
    "dev": {
      "cache": false,
      "persistent": true
    },
    "lint": {
      "dependsOn": ["^build"]
    },
    "format": {},
    "test": {
      "cache": false,
      "persistent": true
    },
    "test:run": {
      "dependsOn": ["^build"]
    },
    "type-check": {
      "dependsOn": ["^build"]
    },
    "clean": {
      "cache": false
    },
    "db:generate": {
      "cache": false
    },
    "db:migrate": {
      "cache": false
    },
    "db:studio": {
      "cache": false,
      "persistent": true
    }
  }
}
